videometer/__init__.py
videometer/hips.py
videometer/setup_helper.py
videometer/vm_utils.py
videometer/tests/test.py
videometer/tests/TestImages/2DGaussianSideBySide.hips
videometer/tests/TestImages/TestEverythingImage_HighCompression.hips
videometer/tests/TestImages/TestEverythingImage_HighQuality.hips
videometer/tests/TestImages/TestEverythingImage_Uncompressed.hips
videometer/tests/TestImages/TestEverythingImage_VeryHighCompression.hips
videometer/tests/TestImages/TestEverythingImage_VeryHighQuality.hips
videometer/tests/TestImages/calibratedImage.hips
videometer-0.0.30.dist-info/licenses/LICENSE.txt
videometer-0.0.30.dist-info/METADATA
videometer-0.0.30.dist-info/WHEEL
videometer-0.0.30.dist-info/top_level.txt
videometer-0.0.30.dist-info/RECORD
