Metadata-Version: 2.4
Name: videometer
Version: 0.0.30
Summary: Videometer python HIPS image reader and writer for Multispectral images
Author: Videometer A/S
Maintainer-email: Aske <asc@videometer.com>
License: The Clear BSD License
Project-URL: Homepage, https://videometer.com
Classifier: Development Status :: 4 - Beta
Classifier: Intended Audience :: Science/Research
Classifier: License :: OSI Approved :: BSD License
Classifier: Operating System :: Microsoft :: Windows
Classifier: Programming Language :: Python
Classifier: Programming Language :: Python :: 3.8
Classifier: Programming Language :: Python :: 3.9
Classifier: Programming Language :: Python :: 3.10
Classifier: Programming Language :: Python :: 3.11
Classifier: Programming Language :: Python :: 3.12
Requires-Python: >=3.8
License-File: LICENSE.txt
Requires-Dist: numpy>=1.19.1
Requires-Dist: matplotlib>=3.4.3
Requires-Dist: pythonnet
Requires-Dist: parameterized
Requires-Dist: requests
Dynamic: license-file
